odoo/addons/mrp_flattened_bom_xlsx/README.rst
odoo/addons/mrp_flattened_bom_xlsx/__init__.py
odoo/addons/mrp_flattened_bom_xlsx/__manifest__.py
odoo/addons/mrp_flattened_bom_xlsx/i18n/it.po
odoo/addons/mrp_flattened_bom_xlsx/i18n/mrp_flattened_bom_xlsx.pot
odoo/addons/mrp_flattened_bom_xlsx/models/__init__.py
odoo/addons/mrp_flattened_bom_xlsx/models/mrp_bom.py
odoo/addons/mrp_flattened_bom_xlsx/readme/CONTRIBUTORS.rst
odoo/addons/mrp_flattened_bom_xlsx/readme/DESCRIPTION.rst
odoo/addons/mrp_flattened_bom_xlsx/readme/USAGE.rst
odoo/addons/mrp_flattened_bom_xlsx/report/__init__.py
odoo/addons/mrp_flattened_bom_xlsx/report/flattened_bom_xlsx.py
odoo/addons/mrp_flattened_bom_xlsx/report/flattened_bom_xlsx.xml
odoo/addons/mrp_flattened_bom_xlsx/static/description/icon.png
odoo/addons/mrp_flattened_bom_xlsx/static/description/index.html
odoo/addons/mrp_flattened_bom_xlsx/tests/__init__.py
odoo/addons/mrp_flattened_bom_xlsx/tests/test_flattened_bom.py
odoo12_addon_mrp_flattened_bom_xlsx-12.0.1.0.0.99.dev11.dist-info/METADATA
odoo12_addon_mrp_flattened_bom_xlsx-12.0.1.0.0.99.dev11.dist-info/WHEEL
odoo12_addon_mrp_flattened_bom_xlsx-12.0.1.0.0.99.dev11.dist-info/top_level.txt
odoo12_addon_mrp_flattened_bom_xlsx-12.0.1.0.0.99.dev11.dist-info/RECORD
